egse/hexapod/__init__.py
egse/hexapod/symetrie/__init__.py
egse/hexapod/symetrie/alpha.py
egse/hexapod/symetrie/dynalpha.py
egse/hexapod/symetrie/hexapod_ui.py
egse/hexapod/symetrie/joran.py
egse/hexapod/symetrie/joran.yaml
egse/hexapod/symetrie/joran_cs.py
egse/hexapod/symetrie/joran_protocol.py
egse/hexapod/symetrie/joran_ui.py
egse/hexapod/symetrie/pmac.py
egse/hexapod/symetrie/pmac_regex.py
egse/hexapod/symetrie/puna.py
egse/hexapod/symetrie/puna.yaml
egse/hexapod/symetrie/puna_cs.py
egse/hexapod/symetrie/puna_protocol.py
egse/hexapod/symetrie/puna_ui.py
egse/hexapod/symetrie/punaplus.py
egse/hexapod/symetrie/zonda.py
egse/hexapod/symetrie/zonda.yaml
egse/hexapod/symetrie/zonda_cs.py
egse/hexapod/symetrie/zonda_devif.py
egse/hexapod/symetrie/zonda_protocol.py
egse/hexapod/symetrie/zonda_ui.py
scripts/cgse_service_plugins.py
symetrie_hexapod-2025.0.9.dist-info/METADATA
symetrie_hexapod-2025.0.9.dist-info/WHEEL
symetrie_hexapod-2025.0.9.dist-info/entry_points.txt
symetrie_hexapod-2025.0.9.dist-info/RECORD
